kubes/__init__.py
kubes/kubes.py
kubes-1.2.0.data/scripts/kubes
kubes-1.2.0.dist-info/METADATA
kubes-1.2.0.dist-info/WHEEL
kubes-1.2.0.dist-info/top_level.txt
kubes-1.2.0.dist-info/RECORD
