Metadata-Version: 2.1
Name: kubes
Version: 1.2.0
Summary: To take care kubectl command
Home-page: https://github.com/Ron-Chang/kubes.git
Author: Ron Chang
Author-email: ron.hsien.chang@gmail.com
License: MIT
Platform: UNKNOWN
Requires-Python: >=3.6
